LICENSE
MANIFEST.in
README.md
VERSION
pyproject.toml
setup.py
openvpn_api/__init__.py
openvpn_api/vpn.py
openvpn_api.egg-info/PKG-INFO
openvpn_api.egg-info/SOURCES.txt
openvpn_api.egg-info/dependency_links.txt
openvpn_api.egg-info/requires.txt
openvpn_api.egg-info/top_level.txt
openvpn_api/models/__init__.py
openvpn_api/models/state.py
openvpn_api/models/stats.py
openvpn_api/util/__init__.py
openvpn_api/util/errors.py
openvpn_api/util/logging.py