Metadata-Version: 2.1
Name: openvpn-api
Version: 0.3.0
Summary: A Python API for the OpenVPN management interface.
Home-page: https://github.com/Jamie-/openvpn-api
Author: Jamie Scott
Author-email: contact@jami.org.uk
License: MIT
Project-URL: Source, https://github.com/Jamie-/openvpn-api
Project-URL: Bug Reports, https://github.com/Jamie-/openvpn-api/issues
Keywords: openvpn monitor management
Platform: UNKNOWN
Classifier: Development Status :: 3 - Alpha
Classifier: Intended Audience :: Developers
Classifier: Intended Audience :: System Administrators
Classifier: License :: OSI Approved :: MIT License
Classifier: Operating System :: OS Independent
Classifier: Programming Language :: Python :: 3.6
Classifier: Programming Language :: Python :: 3.7
Classifier: Programming Language :: Python :: 3.8
Requires-Python: >=3.6
